AUTHORS
ChangeLog
LICENSE
MANIFEST.in
README.rst
requirements.txt
setup.cfg
setup.py
test-requirements.txt
tox.ini
glance_check/__init__.py
glance_check/check.py
glance_check/exception.py
glance_check/shell.py
glance_check.egg-info/PKG-INFO
glance_check.egg-info/SOURCES.txt
glance_check.egg-info/dependency_links.txt
glance_check.egg-info/entry_points.txt
glance_check.egg-info/not-zip-safe
glance_check.egg-info/pbr.json
glance_check.egg-info/requires.txt
glance_check.egg-info/top_level.txt
glance_check/tests/__init__.py
glance_check/tests/test_glance_check.py