Metadata-Version: 1.1
Name: glance-check
Version: 0.0.1.dev1
Summary: Tooling for glance operators to verify the health of diagnose their Glance service.
Home-page: https://github.com/ArdanaCLM
Author: 'SUSE LLC'
Author-email: ardana@googlegroups.com
License: Apache-2.0
Keywords: openstack
Platform: UNKNOWN
Classifier: Development Status :: 3 - Alpha
Classifier: Environment :: Console
Classifier: Environment :: OpenStack
Classifier: Intended Audience :: Developers
Classifier: Intended Audience :: Information Technology
Classifier: License :: OSI Approved :: Apache Software License
Classifier: Operating System :: OS Independent
Classifier: Programming Language :: Python
